swydo/__init__.py
swydo/__version__.py
swydo/client.py
swydo/swydo_api.yml
swydo-1.2019.5.26.dist-info/METADATA
swydo-1.2019.5.26.dist-info/RECORD
swydo-1.2019.5.26.dist-info/WHEEL
swydo-1.2019.5.26.dist-info/top_level.txt
