Metadata-Version: 2.1
Name: swydo
Version: 1.2019.5.26
Summary: Swydo Python SDK (swydo)
Home-page: https://www.github.com/mayple/swydo
Author: Alon Diamant
Author-email: alon@mayple.com
License: UNKNOWN
Platform: UNKNOWN
Classifier: License :: OSI Approved :: MIT License
Classifier: Programming Language :: Python :: 3
Classifier: Operating System :: OS Independent
Requires-Dist: bravado (==10.3.2)
Requires-Dist: ratelimit (==2.2.1)
Requires-Dist: backoff (==1.8.0)
